{
  "baseType": "microsoft.graph.externalItem",
  "properties": [
    {
      "name": "Title",
      "type": "String",
      "isSearchable": true,
      "isQueryable": true,
      "isRetrievable": true,
      "labels": ["title"]
    },
    {
      "name": "Company",
      "type": "String",
      "isSearchable": true,
      "isQueryable": true,
      "isRetrievable": true
    },
    {
      "name": "Ticker",
      "type": "String",
      "isSearchable": true,
      "isQueryable": true,
      "isRetrievable": true
    },
    {
      "name": "Form",
      "type": "String",
      "isSearchable": true,
      "isQueryable": true,
      "isRetrievable": true
    },
    {
      "name": "FilingDate",
      "type": "DateTime",
      "isSearchable": false,
      "isQueryable": true,
      "isRetrievable": true
    },
    {
      "name": "Description",
      "type": "String",
      "isSearchable": true,
      "isQueryable": false,
      "isRetrievable": true
    },
    {
      "name": "Url",
      "type": "String",
      "isSearchable": false,
      "isQueryable": false,
      "isRetrievable": true,
      "labels": ["url"]
    },
    {
      "name": "CIK",
      "type": "String",
      "isSearchable": false,
      "isQueryable": true,
      "isRetrievable": true
    },
    {
      "name": "AccessionNumber",
      "type": "String",
      "isSearchable": false,
      "isQueryable": false,
      "isRetrievable": true
    },
    {
      "name": "Sequence",
      "type": "Int64",
      "isSearchable": false,
      "isQueryable": false,
      "isRetrievable": true
    },
    {
      "name": "Page",
      "type": "Int64",
      "isSearchable": false,
      "isQueryable": false,
      "isRetrievable": true
    }
  ]
}
